setup.cfg
setup.py
chess/__init__.py
chess/urls.py
chess/views.py
django_chess.egg-info/PKG-INFO
django_chess.egg-info/SOURCES.txt
django_chess.egg-info/dependency_links.txt
django_chess.egg-info/not-zip-safe
django_chess.egg-info/top_level.txt