Metadata-Version: 1.0
Name: django-chess
Version: 0.2.1
Summary: Django Chess
Home-page: https://github.com/jacothiart/django-chess
Author: Jaco Thiart
Author-email: jaco@jacothiart.com
License: MIT
Platform: UNKNOWN
